[
  {
    "line": 1,
    "elements": [
      {
        "before": [
          {
            "result": {
              "duration": 536800,
              "status": "passed"
            },
            "match": {
              "location": "CommonStepDefination.intiate(Scenario)"
            }
          },
          {
            "result": {
              "duration": 3273200,
              "status": "passed"
            },
            "match": {
              "location": "Steps.beforeClass(Scenario)"
            }
          }
        ],
        "line": 93,
        "name": "Multiline Serial Items Items for Ambient type item and Verify the ASN details in Manhattan and Vendor Portal",
        "description": "",
        "id": "this-feature-file-contains-atm-customer-vendor-portal-scenarios;multiline-serial-items-items-for-ambient-type-item-and-verify-the-asn-details-in-manhattan-and-vendor-portal",
        "after": [
          {
            "result": {
              "duration": 481158700,
              "status": "passed"
            },
            "match": {
              "location": "Steps.afterClass()"
            }
          }
        ],
        "type": "scenario",
        "keyword": "Scenario",
        "steps": [
          {
            "result": {
              "duration": 1458692600,
              "status": "passed"
            },
            "line": 94,
            "name": "I have excel data",
            "match": {
              "location": "Steps.readExcelData(DataTable)"
            },
            "rows": [
              {
                "cells": [
                  "ATM_KelliScenario004"
                ],
                "line": 95
              }
            ],
            "keyword": "Given "
          },
          {
            "result": {
              "duration": 2012143100,
              "status": "passed"
            },
            "line": 96,
            "name": "User Open the chrome browser using selenium",
            "match": {
              "location": "Steps.open_the_chrome_and_launch_the_application_using_Selenium_with_proxy_enable()"
            },
            "keyword": "Given "
          },
          {
            "result": {
              "duration": 4711807700,
              "status": "passed"
            },
            "line": 97,
            "name": "user logs into the kelli application",
            "match": {
              "location": "StepDefKelli.login_to_kelli_application()"
            },
            "keyword": "And "
          },
          {
            "result": {
              "duration": 160071100,
              "status": "passed"
            },
            "line": 98,
            "name": "user updates data in \"Multi Line Normal\" Kelli Upload Sheet",
            "match": {
              "arguments": [
                {
                  "val": "Multi Line Normal",
                  "offset": 22
                }
              ],
              "location": "StepDefKelli.ASNSheet_Update_data(String)"
            },
            "keyword": "When "
          },
          {
            "result": {
              "duration": 5114506100,
              "status": "passed"
            },
            "line": 99,
            "name": "user upload the \"Multi Line Normal\" Load file in Kelli",
            "match": {
              "arguments": [
                {
                  "val": "Multi Line Normal",
                  "offset": 17
                }
              ],
              "location": "StepDefKelli.upload_Kelli_file(String)"
            },
            "keyword": "And "
          },
          {
            "result": {
              "duration": 3104617800,
              "status": "passed"
            },
            "line": 100,
            "name": "user logout from the kelli application",
            "match": {
              "location": "StepDefKelli.kellilogout()"
            },
            "keyword": "Then "
          },
          {
            "result": {
              "duration": 15330541600,
              "status": "passed"
            },
            "line": 101,
            "name": "user logs into the Manhattan application",
            "match": {
              "location": "StepDefInBound.user_logs_into_the_Manhattan_application()"
            },
            "keyword": "And "
          },
          {
            "result": {
              "duration": 14146681000,
              "status": "passed"
            },
            "line": 102,
            "name": "user fetches the actual ASN number and PO Number uploaded from Optional Field",
            "match": {
              "location": "StepDefInBound.fetch_ASN_And_PO_Number_OptionalField()"
            },
            "keyword": "And "
          },
          {
            "result": {
              "duration": 18528942100,
              "status": "passed"
            },
            "line": 103,
            "name": "user opens ASN screen and searches for the ASN and verify its status \"20 - InTransit\"",
            "match": {
              "arguments": [
                {
                  "val": "20 - InTransit",
                  "offset": 70
                }
              ],
              "location": "StepDefInBound.user_opens_ASN_screen_and_searches_for_the_ASN_and_verify_its_status(String)"
            },
            "keyword": "Then "
          },
          {
            "result": {
              "duration": 23639394100,
              "status": "passed"
            },
            "line": 104,
            "name": "user views ASN, get and verify item details",
            "match": {
              "location": "StepDefInBound.user_views_ASNscreen_and_get_itemdetails()"
            },
            "keyword": "And "
          },
          {
            "result": {
              "duration": 132989210100,
              "status": "passed"
            },
            "line": 105,
            "name": "user log out from application",
            "match": {
              "location": "StepDefInBound.user_log_out_from_application()"
            },
            "keyword": "Then "
          },
          {
            "result": {
              "duration": 231254414800,
              "error_message": "java.lang.AssertionError: Expected condition failed: waiting for visibility of Proxy element for: DefaultElementLocator \u0027By.xpath: //input[@name\u003d\u0027identifier\u0027]\u0027 (tried for 180 second(s) with 500 milliseconds interval) expected [true] but found [false]\r\n\tat org.testng.Assert.fail(Assert.java:111)\r\n\tat org.testng.Assert.failNotEquals(Assert.java:1578)\r\n\tat org.testng.Assert.assertTrue(Assert.java:57)\r\n\tat StepDefinition.StepDefInBound.user_logs_into_the_O2S_application(StepDefInBound.java:1582)\r\n\tat ✽.And user logs into the O2S application(ATMVendorPortalScenariosUpdated.feature:106)\r\n",
              "status": "failed"
            },
            "line": 106,
            "name": "user logs into the O2S application",
            "match": {
              "location": "StepDefInBound.user_logs_into_the_O2S_application()"
            },
            "keyword": "And "
          },
          {
            "result": {
              "status": "skipped"
            },
            "line": 107,
            "name": "user navigate to VendorPortal Tab",
            "match": {
              "location": "StepDefInBound.user_navigate_to_vendorportal_tab()"
            },
            "keyword": "And "
          },
          {
            "result": {
              "status": "skipped"
            },
            "line": 108,
            "name": "user validate the ASN using \"Receipt Number\" search field",
            "match": {
              "arguments": [
                {
                  "val": "Receipt Number",
                  "offset": 29
                }
              ],
              "location": "StepDefInBound.user_validate_the_ASN_using_search_field(String)"
            },
            "keyword": "And "
          },
          {
            "result": {
              "status": "skipped"
            },
            "line": 109,
            "name": "user completes receiving in vendor portal",
            "match": {
              "location": "StepDefInBound.user_completes_receiving_in_vendor_portal()"
            },
            "keyword": "And "
          },
          {
            "result": {
              "status": "skipped"
            },
            "line": 110,
            "name": "user log out from Vendor Portal application",
            "match": {
              "location": "StepDefInBound.user_logout_from_VendorPortal()"
            },
            "keyword": "Then "
          },
          {
            "result": {
              "status": "skipped"
            },
            "line": 111,
            "name": "user logs into the Manhattan application",
            "match": {
              "location": "StepDefInBound.user_logs_into_the_Manhattan_application()"
            },
            "keyword": "And "
          },
          {
            "result": {
              "status": "skipped"
            },
            "line": 112,
            "name": "user opens ASN screen and searches for the ASN and verify its status \"40 - Receiving Verified\"",
            "match": {
              "arguments": [
                {
                  "val": "40 - Receiving Verified",
                  "offset": 70
                }
              ],
              "location": "StepDefInBound.user_opens_ASN_screen_and_searches_for_the_ASN_and_verify_its_status(String)"
            },
            "keyword": "Then "
          },
          {
            "result": {
              "status": "skipped"
            },
            "line": 113,
            "name": "user log out from application",
            "match": {
              "location": "StepDefInBound.user_log_out_from_application()"
            },
            "keyword": "Then "
          }
        ],
        "tags": [
          {
            "line": 92,
            "name": "@InBoundScenario_ATM_MIA-005"
          },
          {
            "line": 92,
            "name": "@IBRegScenarios_ATM"
          },
          {
            "line": 92,
            "name": "@Regression_ATM"
          }
        ]
      }
    ],
    "name": "This feature file contains ATM customer Vendor Portal Scenarios",
    "description": "",
    "id": "this-feature-file-contains-atm-customer-vendor-portal-scenarios",
    "keyword": "Feature",
    "uri": "ATMVendorPortalScenariosUpdated.feature"
  }
]